pyxs/__init__.py
pyxs/_compat.py
pyxs/_internal.py
pyxs/_server.py
pyxs/client.py
pyxs/connection.py
pyxs/exceptions.py
pyxs/helpers.py
pyxs-0.4.1.dist-info/DESCRIPTION.rst
pyxs-0.4.1.dist-info/METADATA
pyxs-0.4.1.dist-info/RECORD
pyxs-0.4.1.dist-info/WHEEL
pyxs-0.4.1.dist-info/metadata.json
pyxs-0.4.1.dist-info/top_level.txt
