Metadata-Version: 2.0
Name: pyxs
Version: 0.4.1
Summary: Pure Python bindings to XenStore.
Home-page: https://github.com/selectel/pyxs
Author: Sergei Lebedev
Author-email: superbobry@gmail.com
License: UNKNOWN
Keywords: xen,xenstore,virtualization
Platform: any
Classifier: Development Status :: 2 - Pre-Alpha
Classifier: Intended Audience :: Developers
Classifier: Programming Language :: Python :: 2
Classifier: Programming Language :: Python :: 2.6
Classifier: Programming Language :: Python :: 2.7
Classifier: Programming Language :: Python :: 3
Classifier: Programming Language :: Python :: 3.4
Classifier: Programming Language :: Python :: 3.5
Classifier: License :: OSI Approved :: GNU Lesser General Public License v3 (LGPLv3)
